data_watcher/__init__.py
data_watcher/app.py
data_watcher/log_dialog.py
data_watcher/process.py
data_watcher/upload_dialog.py
data_watcher_tray-0.0.1.dist-info/LICENSE.txt
data_watcher_tray-0.0.1.dist-info/METADATA
data_watcher_tray-0.0.1.dist-info/WHEEL
data_watcher_tray-0.0.1.dist-info/top_level.txt
data_watcher_tray-0.0.1.dist-info/RECORD
