Metadata-Version: 2.1
Name: data-watcher-tray
Version: 0.0.1
Summary: System tray app and task runner used for watching files
Home-page: https://github.com/techstormpc/data-watcher-tray
Author: TechStorm PC
Author-email: nathan@techstormpc.com
License: MIT
Platform: UNKNOWN
Classifier: Development Status :: 2 - Pre-Alpha
Classifier: Intended Audience :: Information Technology
Classifier: Operating System :: OS Independent
Classifier: License :: OSI Approved :: MIT License
Classifier: Programming Language :: Python :: 3 :: Only
Classifier: Programming Language :: Python :: 3
Classifier: Programming Language :: Python :: 3.8
Classifier: Programming Language :: Python :: 3.9
Classifier: Programming Language :: Python :: 3.10
Requires-Dist: PyQt6 (==6.3.1)
